{
    "items": [
      {
        "questionId": 20,
        "question1": "fndf nfdnfdj",
        "answer": "qdsmndcc qwmnfdsmdf",
        "applicationId": 63,
        "createdAt": "2025-06-05T12:47:35",
        "updatedAt": "2025-06-05T12:47:35"
      },
      {
        "questionId": 19,
        "question1": "fndf n",
        "answer": "qwmnfdsmdf",
        "applicationId": 65,
        "createdAt": "2025-06-05T12:47:27",
        "updatedAt": "2025-06-05T12:47:27"
      },
      {
        "questionId": 18,
        "question1": "dssdjnbgfnfdnfdn fenfnfd fdnfdn",
        "answer": "qdsn fd qd f fdqwdfn fdn qnfknfneede kqdcdfv",
        "applicationId": 65,
        "createdAt": "2025-06-05T12:47:08",
        "updatedAt": "2025-06-05T12:47:08"
      },
      {
        "questionId": 17,
        "question1": "dssdjnbgfnfdnfdn fenfnfd ",
        "answer": "qd f fdqwdfn fdn qnfknfneede kqdcdfv",
        "applicationId": 63,
        "createdAt": "2025-06-05T12:47:00",
        "updatedAt": "2025-06-05T12:47:00"
      },
      {
        "questionId": 16,
        "question1": "dssdjnbgfnfdnfdn ",
        "answer": "qwdfn fdn qnfknfneede kqdcdfv",
        "applicationId": 65,
        "createdAt": "2025-06-05T12:46:53",
        "updatedAt": "2025-06-05T12:46:53"
      },
      {
        "questionId": 15,
        "question1": "dssdjnbgfnfdnfdn ",
        "answer": "qwdfn fdn qnfknfn kqdcdfv",
        "applicationId": 65,
        "createdAt": "2025-06-05T12:46:46",
        "updatedAt": "2025-06-05T12:46:46"
      },
      {
        "questionId": 14,
        "question1": "dssdjnbgfn",
        "answer": "qnfknfn kqdcdfv",
        "applicationId": 65,
        "createdAt": "2025-06-05T12:46:37",
        "updatedAt": "2025-06-05T12:46:37"
      },
      {
        "questionId": 13,
        "question1": "dssd",
        "answer": "qdcdfv",
        "applicationId": 65,
        "createdAt": "2025-06-05T12:46:20",
        "updatedAt": "2025-06-05T12:46:20"
      },
      {
        "questionId": 12,
        "question1": "what is your name?",
        "answer": "haah",
        "applicationId": 59,
        "createdAt": "2025-06-03T20:09:03",
        "updatedAt": "2025-06-03T20:43:37"
      },
      {
        "questionId": 10,
        "question1": "How do you implement defense-in-depth security?",
        "answer": "I apply multiple security controls at different layers of the application.",
        "applicationId": 14,
        "createdAt": "2025-05-17T23:54:20",
        "updatedAt": "2025-05-17T23:54:20"
      }
    ],
    "pageNumber": 1,
    "pageSize": 10,
    "totalCount": 10,
    "totalPages": 1,
    "hasPrevious": false,
    "hasNext": false,
    "currentPage": null
  }